r2c_isg/__init__.py
r2c_isg/apis/__init__.py
r2c_isg/apis/_api.py
r2c_isg/apis/github.py
r2c_isg/apis/npm.py
r2c_isg/apis/pypi.py
r2c_isg/cli.py
r2c_isg/functions/__init__.py
r2c_isg/functions/sample.py
r2c_isg/functions/sort.py
r2c_isg/functions/trim.py
r2c_isg/loaders/__init__.py
r2c_isg/loaders/_loader.py
r2c_isg/loaders/core/__init__.py
r2c_isg/loaders/core/dataset_loader.py
r2c_isg/loaders/core/r2c_loader.py
r2c_isg/loaders/file/__init__.py
r2c_isg/loaders/file/csv_loader.py
r2c_isg/loaders/file/json_loader.py
r2c_isg/loaders/web/__init__.py
r2c_isg/loaders/web/github_loader.py
r2c_isg/loaders/web/npm_loader.py
r2c_isg/loaders/web/pypi_loader.py
r2c_isg/structures/__init__.py
r2c_isg/structures/dataset.py
r2c_isg/structures/projects/__init__.py
r2c_isg/structures/projects/_project.py
r2c_isg/structures/projects/default_project.py
r2c_isg/structures/projects/github_repo.py
r2c_isg/structures/projects/npm_package.py
r2c_isg/structures/projects/pypi_project.py
r2c_isg/structures/versions/__init__.py
r2c_isg/structures/versions/_version.py
r2c_isg/structures/versions/github_commit.py
r2c_isg/structures/versions/npm_version.py
r2c_isg/structures/versions/pypi_release.py
r2c_isg/util.py
r2c_inputset_generator-0.3.2.dist-info/entry_points.txt
r2c_inputset_generator-0.3.2.dist-info/WHEEL
r2c_inputset_generator-0.3.2.dist-info/METADATA
r2c_inputset_generator-0.3.2.dist-info/RECORD
