Metadata-Version: 2.1
Name: r2c-inputset-generator
Version: 0.3.2
Summary: An input set generator for R2C
Home-page: https://r2c.dev
License: Proprietary
Author: Return To Corporation
Author-email: hello@r2c.dev
Requires-Python: >=3.7,<4.0
Classifier: License :: Other/Proprietary License
Classifier: Operating System :: OS Independent
Classifier: Programming Language :: Python :: 3
Classifier: Programming Language :: Python :: 3.7
Classifier: Programming Language :: Python :: 3.8
Requires-Dist: click (>=7.1.1,<8.0.0)
Requires-Dist: click_shell (>=2.0,<3.0)
Requires-Dist: dill (>=0.3.1,<0.4.0)
Requires-Dist: python-dotenv (>=0.12.0,<0.13.0)
Requires-Dist: requests (>=2.23.0,<3.0.0)
Requires-Dist: structures (>=0.9.5,<0.10.0)
Requires-Dist: tqdm (>=4.43.0,<5.0.0)
Requires-Dist: urllib3 (>=1.25.8,<2.0.0)
